{
  "project_info": {
    "project_number": "597572712313",
    "project_id": "bies-e28ca",
    "storage_bucket": "bies-e28ca.appspot.com"
  },
  "client": [
    {
      "client_info": {
        "mobilesdk_app_id": "1:597572712313:android:7aa708d1e65e337e8261a8",
        "android_client_info": {
          "package_name": "com.example.bies"
        }
      },
      "oauth_client": [
        {
          "client_id": "597572712313-pch4n97s26r8s72dhrpv9un7dqddlqfv.apps.googleusercontent.com",
          "client_type": 3
        }
      ],
      "api_key": [
        {
          "current_key": "AIzaSyAX1asE_QKDS9Zs7MjFQeOHX42DS7W9OTg"
        }
      ],
      "services": {
        "appinvite_service": {
          "other_platform_oauth_client": [
            {
              "client_id": "597572712313-pch4n97s26r8s72dhrpv9un7dqddlqfv.apps.googleusercontent.com",
              "client_type": 3
            }
          ]
        }
      }
    }
  ],
  "configuration_version": "1"
}